object_symbols_parser/__init__.py
object_symbols_parser/cli.py
object_symbols_parser/object_symbols_parser.py
object_symbols_parser-0.1.2.dist-info/licenses/LICENSE
object_symbols_parser-0.1.2.dist-info/METADATA
object_symbols_parser-0.1.2.dist-info/WHEEL
object_symbols_parser-0.1.2.dist-info/entry_points.txt
object_symbols_parser-0.1.2.dist-info/top_level.txt
object_symbols_parser-0.1.2.dist-info/RECORD
