Metadata-Version: 2.4
Name: object_symbols_parser
Version: 0.1.2
Summary: Object symbol table wrangler. Useful for finding static memory and code size usage in embedded systems.
Author-email: Simon Hobbs <simon.hobbs@electrooptical.net>
License-Expression: MIT
Project-URL: github, https://github.com/snhobbs/object_symbols_parser
Keywords: object_symbols_parser,embedded,mcu,arm,binary,elf
Classifier: Development Status :: 2 - Pre-Alpha
Classifier: Intended Audience :: Developers
Classifier: Natural Language :: English
Classifier: Programming Language :: Python :: 3
Requires-Python: >=3.8
License-File: LICENSE
Requires-Dist: pandas
Requires-Dist: click
Dynamic: license-file
